{"name":"链接脚本","slug":"链接脚本","count":1,"postlist":[{"title":"连接脚本浅谈","slug":"UBOOT/链接脚本浅谈","date":"2018-05-26T03:54:32.000Z","updated":"2018-09-15T04:17:53.216Z","comments":true,"path":"api/articles/UBOOT/链接脚本浅谈.json","excerpt":"<p>对于<code>.lds</code>文件，它定义了整个程序编译之后的连接过程，决定了一个可执行程序的各个段的存储位置。虽然现在我还没怎么用它，但感觉还是挺重要的，有必要了解一下。</p>","keywords":null,"cover":null,"content":null,"text":"对于.lds文件，它定义了整个程序编译之后的连接过程，决定了一个可执行程序的各个段的存储位置。虽然现在我还没怎么用它，但感觉还是挺重要的，有必要了解一下。一、概论每一个链接过程^1.1  都由链接脚本[^1.2]控制。链接脚本主要用于规定如何把输入文件内的section放入输出文","link":"","raw":null,"photos":[],"categories":[{"name":"链接脚本","slug":"链接脚本","count":1,"path":"api/categories/链接脚本.json"}],"tags":[{"name":"链接脚本","slug":"链接脚本","count":1,"path":"api/tags/链接脚本.json"}]}]}