{"name":"嵌入式","slug":"嵌入式","count":2,"postlist":[{"title":"ARM_01_嵌入式系统概述","slug":"ARM/ARM_01","date":"2018-02-01T06:00:15.000Z","updated":"2018-06-04T13:25:39.909Z","comments":true,"path":"api/articles/ARM/ARM_01.json","excerpt":"<p><strong>1 嵌入式的概念</strong> √<br><strong>2 嵌入式系统的特点</strong> √<br><strong>3 嵌入式系统的组成</strong> √<br><strong>4 ARM内核种类</strong> √<br><strong>5 ARM内核内部的寄存器</strong> √</p>","keywords":null,"cover":null,"content":null,"text":"1 嵌入式的概念 √<br>2 嵌入式系统的特点 √<br>3 嵌入式系统的组成 √<br>4 ARM内核种类 √<br>5 ARM内核内部的寄存器 √前言我对于ARM的学习是基于ARM公司 CotexA9 架构处理器核心 samsung（三星公司） 提供的一款型号为 Exyno","link":"","raw":null,"photos":[],"categories":[{"name":"嵌入式","slug":"嵌入式","count":2,"path":"api/categories/嵌入式.json"}],"tags":[{"name":"ARM","slug":"ARM","count":2,"path":"api/tags/ARM.json"}]},{"title":"ARM_02_环境搭建","slug":"ARM/ARM_02","date":"2018-02-03T05:35:42.000Z","updated":"2018-06-04T14:52:18.576Z","comments":true,"path":"api/articles/ARM/ARM_02.json","excerpt":"<p><strong>1 交叉编译工具的安装</strong> √<br><strong>2 编译Uboot</strong> √<br><strong>3 安装Kermit</strong> √<br><strong>4 Minicom</strong> √<br><strong>5 Uboot的命令</strong> √<br><strong>6 Dnw工具的安装</strong> √<br><strong>7 往Emmc烧写Uboot</strong> √</p>","keywords":null,"cover":"https://wx4.sinaimg.cn/mw690/0079ID0Dly1frzifvzrz0j30bq09ngnl.jpg","content":null,"text":"1 交叉编译工具的安装 √<br>2 编译Uboot √<br>3 安装Kermit √<br>4 Minicom √<br>5 Uboot的命令 √<br>6 Dnw工具的安装 √<br>7 往Emmc烧写Uboot √一. 交叉编译工具的安装安装交叉编译工具到/opt1<br","link":"","raw":null,"photos":[],"categories":[{"name":"嵌入式","slug":"嵌入式","count":2,"path":"api/categories/嵌入式.json"}],"tags":[{"name":"ARM","slug":"ARM","count":2,"path":"api/tags/ARM.json"}]}]}